iverlog_tutorials/Sequential_logic/switch_state.v
module top(a, b, clk, z);

    input a, b, clk;
    output z;
    
    // reg is a collection of flipflops
    // single bit reg would just be one flipflop
    reg d = 0;

    assign z = d;

    // state machine
    always @(posedge clk) begin
        d = a ^ b ^ d;
    end

endmodule

iverlog_tutorials/Sequential_logic/switch_state_tb.v
`timescale 1ns/1ns
`include "switch_state.v"

module switch_state_tb;

    reg a, b, clk = 0;
    wire z;

    top UUT(a, b, clk, z);
    
    always begin
        clk = ~clk; // toggle clock
        #10;
    end

    initial begin
        $dumpfile("./switch_state_tb.vcd");
        $dumpvars(0, switch_state_tb);

        {a, b} = 2'b00; #20;
        {a, b} = 2'b11; #20;
        {a, b} = 2'b01; #20;
        {a, b} = 2'b00; #20;
        {a, b} = 2'b11; #20;
        {a, b} = 2'b10; #20;
        {a, b} = 2'b01; #20;
        {a, b} = 2'b10; #20;
        $finish;
    end

endmodule

iverlog_tutorials/Sequential_logic/switch_state_tb.vcd
$date
	Tue Oct 15 23:30:16 2024
$end
$version
	Icarus Verilog
$end
$timescale
	1ns
$end
$scope module switch_state_tb $end
$var wire 1 ! z $end
$var reg 1 " a $end
$var reg 1 # b $end
$var reg 1 $ clk $end
$scope module UUT $end
$var wire 1 " a $end
$var wire 1 # b $end
$var wire 1 $ clk $end
$var wire 1 ! z $end
$var reg 1 % d $end
$upscope $end
$upscope $end
$enddefinitions $end
#0
$dumpvars
0%
1$
0#
0"
0!
$end
#10
0$
#20
1$
1"
1#
#30
0$
#40
1!
1%
1$
0"
#50
0$
#60
1$
0#
#70
0$
#80
1$
1"
1#
#90
0$
#100
0!
0%
1$
0#
#110
0$
#120
1!
1%
1$
0"
1#
#130
0$
#140
0!
0%
1$
1"
0#
#150
0$
#160
1!
1%
1$
