iverlog_tutorials/comparator/greater_than.v
module greater_than (a, b, f);

    input [1:0] a,b;
    output f;
    
    // assign f = a > b;

    assign f = (a[1] & ~b[1]) | ((a[1]~^b[1]) & (a[0] & ~b[0]));
    //assign f = a[1] & ~b[1] | a[1] ~^ b[1] & a[0] & ~b[0]; // wrong!

endmodule

iverlog_tutorials/comparator/greater_than_tb.v
`timescale 1ns/ 1ns
`include "greater_than.v"

module greater_than_tb;

    reg [1:0] a, b;
    wire f;

    greater_than uut (a, b, f);

    initial begin

        $dumpfile("./greater_than_tb.vcd");
        $dumpvars(0, greater_than_tb);

        {a, b} = 4'd0; #20;
        {a, b} = 4'd1; #20;
        {a, b} = 4'd2; #20;
        {a, b} = 4'd3; #20;
        {a, b} = 4'd4; #20;
        {a, b} = 4'd5; #20;
        {a, b} = 4'd6; #20;
        {a, b} = 4'd7; #20;
        {a, b} = 4'd8; #20;
        {a, b} = 4'd9; #20;
        {a, b} = 4'd10; #20;
        {a, b} = 4'd11; #20;
        {a, b} = 4'd12; #20;
        {a, b} = 4'd13; #20;
        {a, b} = 4'd14; #20;
        {a, b} = 4'd15; #20;

        $display("Test is complete.");
    end

endmodule

iverlog_tutorials/comparator/greater_than_tb.vcd
$date
	Tue Oct 15 21:57:20 2024
$end
$version
	Icarus Verilog
$end
$timescale
	1ns
$end
$scope module greater_than_tb $end
$var wire 1 ! f $end
$var reg 2 " a [1:0] $end
$var reg 2 # b [1:0] $end
$scope module uut $end
$var wire 2 $ a [1:0] $end
$var wire 2 % b [1:0] $end
$var wire 1 ! f $end
$upscope $end
$upscope $end
$enddefinitions $end
#0
$dumpvars
b0 %
b0 $
b0 #
b0 "
0!
$end
#20
b1 #
b1 %
#40
b10 #
b10 %
#60
b11 #
b11 %
#80
1!
b1 "
b1 $
b0 #
b0 %
#100
0!
b1 #
b1 %
#120
b10 #
b10 %
#140
b11 #
b11 %
#160
1!
b10 "
b10 $
b0 #
b0 %
#180
b1 #
b1 %
#200
0!
b10 #
b10 %
#220
b11 #
b11 %
#240
1!
b11 "
b11 $
b0 #
b0 %
#260
b1 #
b1 %
#280
b10 #
b10 %
#300
0!
b11 #
b11 %
